README.md
pyproject.toml
setup.py
paragon/__init__.py
paragon/__main__.py
paragon/animate.py
paragon/benchmark.py
paragon/cli.py
paragon/exporter.py
paragon/mark.py
paragon/stats.py
paragon/utils.py
paragon.egg-info/PKG-INFO
paragon.egg-info/SOURCES.txt
paragon.egg-info/dependency_links.txt
paragon.egg-info/entry_points.txt
paragon.egg-info/requires.txt
paragon.egg-info/top_level.txt
tests/__init__.py
tests/test_mark.py
tests/test_stats.py