Metadata-Version: 2.1
Name: paragon
Version: 1.0.0
Summary: A tiny command line benchmarking utility
Home-page: http://packages.python.org/paragon
Author: Liam Scalzulli
Author-email: liamscalzulli@gmail.com
License: BSD
Project-URL: Source Code, https://github.com/terror/paragon
Keywords: benchmark,benchmarking
Platform: UNKNOWN
Classifier: Development Status :: 3 - Alpha
Classifier: Topic :: Utilities
Classifier: License :: OSI Approved :: MIT License
Requires-Python: >=3.7
